SevenWondersEnv/_version.py
SevenWondersEnv/setup.py
SevenWondersEnv/SevenWonEnv/__init__.py
SevenWondersEnv/SevenWonEnv/envs/SevenWonderEnv.py
SevenWondersEnv/SevenWonEnv/envs/__init__.py
SevenWondersEnv/SevenWonEnv/envs/gameLog.txt
SevenWondersEnv/SevenWonEnv/envs/main.py
SevenWondersEnv/SevenWonEnv/envs/model.py
SevenWondersEnv/SevenWonEnv/envs/GameLog/gameLog0.txt
SevenWondersEnv/SevenWonEnv/envs/Graph/100.png
SevenWondersEnv/SevenWonEnv/envs/Graph/200.png
SevenWondersEnv/SevenWonEnv/envs/Graph/300.png
SevenWondersEnv/SevenWonEnv/envs/Graph/400.png
SevenWondersEnv/SevenWonEnv/envs/Test/allTests.py
SevenWondersEnv/SevenWonEnv/envs/mainGameEnv/Personality.py
SevenWondersEnv/SevenWonEnv/envs/mainGameEnv/PlayerClass.py
SevenWondersEnv/SevenWonEnv/envs/mainGameEnv/WonderClass.py
SevenWondersEnv/SevenWonEnv/envs/mainGameEnv/cardClass.py
SevenWondersEnv/SevenWonEnv/envs/mainGameEnv/loggers.txt
SevenWondersEnv/SevenWonEnv/envs/mainGameEnv/main.py
SevenWondersEnv/SevenWonEnv/envs/mainGameEnv/mainHelper.py
SevenWondersEnv/SevenWonEnv/envs/mainGameEnv/resourceClass.py
SevenWondersEnv/SevenWonEnv/envs/mainGameEnv/stageClass.py
SevenWondersEnv/SevenWonEnv/envs/mainGameEnv/tester.py
SevenWondersEnv/SevenWonEnv/envs/mainGameEnv/Card/card_list.json
SevenWondersEnv/SevenWonEnv/envs/mainGameEnv/Card/effect_list.json
SevenWondersEnv/SevenWonEnv/envs/mainGameEnv/Card/resources_list.json
SevenWondersEnv/SevenWonEnv/envs/mainGameEnv/Card/wonders_list.json
SevenWondersEnv/SevenWonEnv.egg-info/SOURCES.txt
SevenWondersEnv/SevenWonEnv.egg-info/dependency_links.txt
SevenWondersEnv/SevenWonEnv.egg-info/requires.txt
SevenWondersEnv/SevenWonEnv.egg-info/top_level.txt
7Wonder_RL_Lib-0.1.1.dist-info/LICENSE
7Wonder_RL_Lib-0.1.1.dist-info/METADATA
7Wonder_RL_Lib-0.1.1.dist-info/WHEEL
7Wonder_RL_Lib-0.1.1.dist-info/top_level.txt
7Wonder_RL_Lib-0.1.1.dist-info/RECORD
