Metadata-Version: 2.1
Name: 7Wonder-RL-Lib
Version: 0.1.1
Summary: Gymnasium Environment for the game Seven Wonders
Author-email: Phudis Dawieang <pd2654@columbia.edu>
License: MIT License
Project-URL: repository, https://github.com/MirrorCraze/7Wonder-RL-Lib
Classifier: Development Status :: 2 - Pre-Alpha
Classifier: Programming Language :: Python :: Implementation :: CPython
Classifier: Programming Language :: Python :: Implementation :: PyPy
Classifier: Programming Language :: Python :: 3.9
Classifier: Programming Language :: Python :: 3.10
Classifier: Programming Language :: Python :: 3.11
Requires-Python: >=3.9
License-File: LICENSE
Requires-Dist: gymnasium
Provides-Extra: develop
Requires-Dist: black (>=22) ; extra == 'develop'
Requires-Dist: bump2version (>=1.0.0) ; extra == 'develop'
Requires-Dist: check-manifest ; extra == 'develop'
Requires-Dist: pylint ; extra == 'develop'
Requires-Dist: mypy ; extra == 'develop'
Requires-Dist: twine ; extra == 'develop'
Requires-Dist: wheel ; extra == 'develop'
Requires-Dist: coverage ; extra == 'develop'
